setup.py
pincode_directory/__init__.py
pincode_directory/pincodes.py
pincode_directory/search.py
pincode_directory.egg-info/PKG-INFO
pincode_directory.egg-info/SOURCES.txt
pincode_directory.egg-info/dependency_links.txt
pincode_directory.egg-info/not-zip-safe
pincode_directory.egg-info/top_level.txt