Metadata-Version: 1.0
Name: pincode-directory
Version: 1.0.0
Summary: Small directory to get the deatials of indian pincodes.
Home-page: https://github.com/36rahu/pincode_directory
Author: Rahul K P
Author-email: 36rahu@gmail.com
License: MIT
Platform: UNKNOWN
